application/__init__.py
application/dtos/__init__.py
application/dtos/fix_directory_result.py
application/dtos/fix_file_result.py
application/use_cases/__init__.py
application/use_cases/fix_directory_indentation.py
application/use_cases/fix_file_indentation.py
domain/__init__.py
domain/entities/__init__.py
domain/entities/multiline_string.py
domain/entities/source_file.py
domain/exceptions/__init__.py
domain/exceptions/base_exceptions.py
domain/exceptions/entity_exceptions.py
domain/exceptions/file_exceptions.py
domain/exceptions/parsing_exceptions.py
domain/repositories/__init__.py
domain/repositories/file_repository.py
domain/repositories/parser_repository.py
infrastructure/__init__.py
infrastructure/config.py
infrastructure/container.py
infrastructure/file_system/__init__.py
infrastructure/file_system/file_system_repository.py
infrastructure/parsers/__init__.py
infrastructure/parsers/ast_parser.py
presentation/__init__.py
presentation/cli/__init__.py
presentation/cli/cli.py
pytriple-1.0.0.dist-info/licenses/LICENSE
pytriple-1.0.0.dist-info/METADATA
pytriple-1.0.0.dist-info/WHEEL
pytriple-1.0.0.dist-info/entry_points.txt
pytriple-1.0.0.dist-info/top_level.txt
pytriple-1.0.0.dist-info/RECORD
